{
  "$schema": "../gen/schemas/desktop-schema.json",
  "identifier": "default",
  "description": "Capability for the main window",
  "windows": ["main"],
  "permissions": [
    "core:default",
    "core:window:allow-start-dragging",
    "core:window:allow-is-fullscreen",
    "core:window:allow-is-maximized",
    "core:window:allow-maximize",
    "core:window:allow-unmaximize",
    "core:window:allow-minimize",
    "core:window:allow-close",
    "core:event:allow-listen",
    "opener:default",
    "autostart:allow-enable",
    "autostart:allow-disable",
    "autostart:allow-is-enabled",
    "stronghold:default",
    "updater:default"
  ]
}
